mesh_sandbox/__init__.py
mesh_sandbox/api.py
mesh_sandbox/common/__init__.py
mesh_sandbox/common/constants.py
mesh_sandbox/common/exceptions.py
mesh_sandbox/common/fernet.py
mesh_sandbox/common/handler_helpers.py
mesh_sandbox/common/messaging.py
mesh_sandbox/common/mex_headers.py
mesh_sandbox/conftest.py
mesh_sandbox/dependencies.py
mesh_sandbox/handlers/__init__.py
mesh_sandbox/handlers/admin.py
mesh_sandbox/handlers/handshake.py
mesh_sandbox/handlers/inbox.py
mesh_sandbox/handlers/lookup.py
mesh_sandbox/handlers/outbox.py
mesh_sandbox/handlers/tracking.py
mesh_sandbox/models/__init__.py
mesh_sandbox/models/mailbox.py
mesh_sandbox/models/message.py
mesh_sandbox/models/workflow.py
mesh_sandbox/plugins/__init__.py
mesh_sandbox/routers/__init__.py
mesh_sandbox/routers/admin.py
mesh_sandbox/routers/handshake.py
mesh_sandbox/routers/inbox.py
mesh_sandbox/routers/inbox_count.py
mesh_sandbox/routers/lookup.py
mesh_sandbox/routers/outbox.py
mesh_sandbox/routers/request_logging.py
mesh_sandbox/routers/tracking.py
mesh_sandbox/routers/update.py
mesh_sandbox/store/__init__.py
mesh_sandbox/store/base.py
mesh_sandbox/store/canned_store.py
mesh_sandbox/store/data/mailboxes/X26ABC1/in/SIMPLE_MESSAGE/1
mesh_sandbox/store/data/mailboxes/X26ABC1/in/SIMPLE_MESSAGE.json
mesh_sandbox/store/data/mailboxes/X26ABC1/in/UNDELIVERED_MESSAGE/1
mesh_sandbox/store/data/mailboxes/X26ABC1/in/UNDELIVERED_MESSAGE.json
mesh_sandbox/store/data/mailboxes/X26ABC2/in/CHUNKED_MESSAGE_GZ/1
mesh_sandbox/store/data/mailboxes/X26ABC2/in/CHUNKED_MESSAGE_GZ/2
mesh_sandbox/store/data/mailboxes/X26ABC2/in/CHUNKED_MESSAGE_GZ.json
mesh_sandbox/store/data/mailboxes.jsonl
mesh_sandbox/store/data/workflows.jsonl
mesh_sandbox/store/file_store.py
mesh_sandbox/store/memory_store.py
mesh_sandbox/store/serialisation.py
mesh_sandbox/test_plugin/__init__.py
mesh_sandbox/test_plugin/example_plugin.py
mesh_sandbox/test_plugin/example_plugin.txt
mesh_sandbox/tests/__init__.py
mesh_sandbox/tests/admin.py
mesh_sandbox-1.0.36.dist-info/METADATA
mesh_sandbox-1.0.36.dist-info/WHEEL
mesh_sandbox-1.0.36.dist-info/licenses/LICENSE
mesh_sandbox-1.0.36.dist-info/RECORD
