Metadata-Version: 2.4
Name: mesh-sandbox
Version: 1.0.36
Summary: NHSDigital mesh sandbox, a locally testable version of the MESH api
License: MIT
License-File: LICENSE
Author: spinecore
Requires-Python: >=3.11,<3.14.0
Classifier: License :: OSI Approved :: MIT License
Classifier: Programming Language :: Python :: 3
Classifier: Programming Language :: Python :: 3.11
Classifier: Programming Language :: Python :: 3.12
Classifier: Programming Language :: Python :: 3.13
Requires-Dist: cryptography (>=44.0.1,<47)
Requires-Dist: fastapi (>=0.110.0,<0.129.0)
Requires-Dist: gunicorn (>=21.2,<24.0)
Requires-Dist: mesh-client (>=4.0.1,<5.0.0)
Requires-Dist: python-dateutil (>=2.8.2,<3.0.0)
Requires-Dist: types-python-dateutil (>=2.8.9,<3.0.0)
Requires-Dist: typing-extensions (>=4.10.0)
Requires-Dist: uvicorn (>=0.23.2,<0.41.0)
